crostab/__init__.py
crostab/convert/__init__.py
crostab/crostab/__init__.py
crostab/enum/__init__.py
crostab/enum/keys/__init__.py
crostab/series/__init__.py
crostab/structs/__init__.py
crostab/structs/cell.py
crostab/structs/field.py
crostab/structs/filter.py
crostab/structs/table_spec.py
crostab/table/__init__.py
crostab/types/__init__.py
crostab/utils/__init__.py
crostab/utils/infer_column_type.py
crostab-0.0.11.dist-info/WHEEL
crostab-0.0.11.dist-info/METADATA
crostab-0.0.11.dist-info/RECORD
