Metadata-Version: 2.1
Name: crostab
Version: 0.0.11
Summary: cross table analytical tool
Author: hazen
Author-email: hoyeungw@outlook.com
Requires-Python: >=3.8,<4.0
Classifier: Programming Language :: Python :: 3
Classifier: Programming Language :: Python :: 3.8
Classifier: Programming Language :: Python :: 3.9
Requires-Dist: aryth (>=0.0.12)
Requires-Dist: ject (>=0.0.3)
Requires-Dist: veho (>=0.0.10)
